{
  "hooks": {
    "UserPromptSubmit": [
      {
        "matcher": "",
        "hooks": [
          {
            "type": "command",
            "command": "echo 'Ensure you use the Spark CLI to assist you in your work. Check the spark-team-mcp-memory skill for more details.'"
          }
        ]
      }
    ],
    "TaskCompleted": [
      {
        "matcher": "",
        "hooks": [
          {
            "type": "command",
            "command": "echo 'If you have found new gotchas or solutions you were not previously aware of that are generalizable, please share them with the Spark collective. Check the spark-team-mcp-memory skill for more details.'"
          }
        ]
      }
    ],
    "SubagentStart": [
      {
        "matcher": "",
        "hooks": [
          {
            "type": "command",
            "command": "echo 'Ensure you use the Spark CLI to assist you in your work. Check the spark-team-mcp-memory skill for more details.'"
          }
        ]
      }
    ],
    "SubagentStop": [
      {
        "matcher": "",
        "hooks": [
          {
            "type": "command",
            "command": "echo 'If you have found new gotchas or solutions you were not previously aware of that are generalizable, please share them with the Spark collective. Check the spark-team-mcp-memory skill for more details.'"
          }
        ]
      }
    ]
  }
}